lai/__init__.py
lai/__main__.py
lai/scripts/lai.py
lai-2019.0.1.dist-info/METADATA
lai-2019.0.1.dist-info/WHEEL
lai-2019.0.1.dist-info/top_level.txt
lai-2019.0.1.dist-info/RECORD
