Metadata-Version: 2.1
Name: lai
Version: 2019.0.1
Summary: yet a python demo
Home-page: https://github.com/chaosannals/lai
Author: chaosannals
Author-email: chaosannals@gmail.com
License: MIT
Keywords: lai python package egg
Platform: any
Classifier: License :: OSI Approved :: MIT License
Classifier: Intended Audience :: Developers
Classifier: Operating System :: OS Independent
Classifier: Programming Language :: Python :: 3
Classifier: Programming Language :: Python :: 3.2
Classifier: Programming Language :: Python :: 3.3
Classifier: Programming Language :: Python :: 3.4
Classifier: Programming Language :: Python :: 3.5
Classifier: Programming Language :: Python :: 3.6
Classifier: Programming Language :: Python :: 3.7
Classifier: Programming Language :: Python :: 3.8
Requires-Dist: imagehash
Requires-Dist: scipy
Requires-Dist: vptree
